ens/__init__.py
ens/_normalization.py
ens/abis.py
ens/async_ens.py
ens/auto.py
ens/base_ens.py
ens/constants.py
ens/contract_data.py
ens/ens.py
ens/exceptions.py
ens/utils.py
ens/specs/nf.json
ens/specs/normalization_spec.json
web3/__init__.py
web3/constants.py
web3/datastructures.py
web3/exceptions.py
web3/geth.py
web3/logs.py
web3/main.py
web3/manager.py
web3/method.py
web3/module.py
web3/net.py
web3/py.typed
web3/testing.py
web3/tracing.py
web3/types.py
web3/_utils/__init__.py
web3/_utils/abi.py
web3/_utils/abi_element_identifiers.py
web3/_utils/async_caching.py
web3/_utils/async_transactions.py
web3/_utils/batching.py
web3/_utils/blocks.py
web3/_utils/contracts.py
web3/_utils/datatypes.py
web3/_utils/decorators.py
web3/_utils/empty.py
web3/_utils/encoding.py
web3/_utils/ens.py
web3/_utils/error_formatters_utils.py
web3/_utils/events.py
web3/_utils/fee_utils.py
web3/_utils/filters.py
web3/_utils/formatters.py
web3/_utils/http.py
web3/_utils/http_session_manager.py
web3/_utils/hypothesis.py
web3/_utils/math.py
web3/_utils/method_formatters.py
web3/_utils/module.py
web3/_utils/normalizers.py
web3/_utils/rpc_abi.py
web3/_utils/threads.py
web3/_utils/transactions.py
web3/_utils/type_conversion.py
web3/_utils/utility_methods.py
web3/_utils/validation.py
web3/_utils/windows.py
web3/_utils/caching/__init__.py
web3/_utils/caching/caching_utils.py
web3/_utils/caching/request_caching_validation.py
web3/_utils/compat/__init__.py
web3/_utils/contract_sources/__init__.py
web3/_utils/contract_sources/compile_contracts.py
web3/_utils/contract_sources/contract_data/__init__.py
web3/_utils/contract_sources/contract_data/_custom_contract_data.py
web3/_utils/contract_sources/contract_data/ambiguous_function_contract.py
web3/_utils/contract_sources/contract_data/arrays_contract.py
web3/_utils/contract_sources/contract_data/bytes_contracts.py
web3/_utils/contract_sources/contract_data/constructor_contracts.py
web3/_utils/contract_sources/contract_data/contract_caller_tester.py
web3-7.11.1.dist-info/LICENSE
web3-7.11.1.dist-info/METADATA
web3-7.11.1.dist-info/WHEEL
web3-7.11.1.dist-info/top_level.txt
web3-7.11.1.dist-info/RECORD
